{
    "Allet":{"n":"알레트","t":"411021"},
    "Amelia":{"n":"아멜리아","t":"031231"},
    "Ashur":{"n":"에슈르","t":"130212"},
    "Aya":{"n":"아야","t":"030116"},
    "Belita":{"n":"벨리타","t":"330216"},
    "Beni":{"n":"베니","t":"221013"},
    "BigWood":{"n":"빅우드","t":"421025"},
    "Butter":{"n":"버터","t":"231213"},
    "Canna":{"n":"칸나","t":"231211"},
    "Carren":{"n":"카렌","t":"210232"},
    "Chloe":{"n":"클로에","t":"330022"},
    "Chopi":{"n":"쵸피","t":"111113"},
    "Cuee":{"n":"큐이","t":"410132"},
    "Daya":{"n":"다야","t":"430210"},
    "Diana":{"n":"디아나","t":"330133"},
    "Elena":{"n":"엘레나","t":"031111"},
    "Epica":{"n":"에피카","t":"231113"},
    "Erpin":{"n":"에르핀","t":"430212"},
    "Espi":{"n":"에스피","t":"020224"},
    "Festa":{"n":"페스타","t":"121031"},
    "Fricle":{"n":"프리클","t":"030116"},
    "Gabia":{"n":"가비아","t":"420135"},
    "Hilde":{"n":"힐데","t":"130131"},
    "Ifrit":{"n":"이프리트","t":"320015"},
    "Jade":{"n":"제이드","t":"030110"},
    "Jubee":{"n":"쥬비","t":"221115"},
    "Kidian":{"n":"키디언","t":"131010"},
    "Kommy":{"n":"코미","t":"131023"},
    "Lazy":{"n":"레이지","t":"011211"},
    "Levi":{"n":"레비","t":"121116"},
    "MaestroMK2":{"n":"마에스트로 2호","t":"321021"},
    "Mago":{"n":"마고","t":"420133"},
    "Maison":{"n":"메죵","t":"311214"},
    "Marie":{"n":"마리","t":"221112"},
    "Mayo":{"n":"마요","t":"321212"},
    "Meluna":{"n":"멜루나","t":"030235"},
    "Mynx":{"n":"밍스","t":"211013"},
    "Naia":{"n":"나이아","t":"430135"},
    "Ner":{"n":"네르","t":"330032"},
    "Patula":{"n":"파트라","t":"011012"},
    "Posher":{"n":"포셔","t":"130236"},
    "Rim":{"n":"림","t":"131014"},
    "Rohne":{"n":"로네","t":"421021"},
    "Rude":{"n":"루드","t":"231020"},
    "Rufo":{"n":"루포","t":"231113"},
    "Sari":{"n":"사리","t":"411114"},
    "Selline":{"n":"셀리네","t":"230024"},
    "Shady":{"n":"셰이디","t":"331014"},
    "Silphir":{"n":"실피르","t":"121110"},
    "Sist":{"n":"시스트","t":"331110"},
    "Speaki":{"n":"스피키","t":"420234"},
    "Sylla":{"n":"실라","t":"031215"},
    "Taida":{"n":"타이다","t":"211211"},
    "Tig":{"n":"티그","t":"231013"},
    "Ui":{"n":"우이","t":"230135"},
    "Velvet":{"n":"벨벳","t":"031026"},
    "Veroo":{"n":"베루","t":"111114"},
    "Vivi":{"n":"비비","t":"430020"},
    "xXionx":{"n":"시온 더 다크불릿","t":"131214"},
    "Yumimi":{"n":"유미미","t":"311213"}
}